README.md
setup.py
pandas3/__init__.py
pandas3/etherscan.py
pandas3/logging_util.py
pandas3/transformer.py
test/__init__.py
test/pandas/__init__.py
test/pandas/test_transformer.py
test/resources/__init__.py
web3_pandas.egg-info/PKG-INFO
web3_pandas.egg-info/SOURCES.txt
web3_pandas.egg-info/dependency_links.txt
web3_pandas.egg-info/requires.txt
web3_pandas.egg-info/top_level.txt