Metadata-Version: 2.1
Name: web3-pandas
Version: 0.3.1
Summary: Pandas extension utils for Web3
Home-page: https://github.com/tellery/web3-pandas
Author: songv
Author-email: songwei@iftech.io
License: UNKNOWN
Project-URL: Bug Reports, https://github.com/tellery/web3-pandas/issues
Project-URL: Source, https://github.com/tellery/web3-pandas
Keywords: web3,pandas
Platform: UNKNOWN
Classifier: Development Status :: 5 - Production/Stable
Classifier: Intended Audience :: Developers
Classifier: License :: OSI Approved :: MIT License
Classifier: Programming Language :: Python :: 3
Classifier: Programming Language :: Python :: 3.6
Classifier: Programming Language :: Python :: 3.7
Classifier: Programming Language :: Python :: 3.8
Classifier: Programming Language :: Python :: 3.9
Requires-Python: >=3.6,<4
